pynvg
