Metadata-Version: 2.1
Name: pynvg
Version: 0.1.4
Summary: pynvg is a general purpose library by NVG
Home-page: https://github.com/lonagi/pynvg
Author: lonagi
Author-email: lonagi22@gmail.com
License: MIT
Project-URL: Bug Tracker, https://github.com/lonagi/pynvg/issues
Project-URL: Changelog, https://github.com/lonagi/pynvg/blob/master/CHANGELOG.md
Project-URL: Source Code, https://github.com/lonagi/pynvg
Keywords: pynvg,python,general
Platform: any
Classifier: Development Status :: 2 - Pre-Alpha
Classifier: Intended Audience :: Developers
Classifier: License :: OSI Approved :: MIT License
Classifier: Operating System :: OS Independent
Classifier: Programming Language :: Python
Classifier: Programming Language :: Python :: 3.4
Classifier: Programming Language :: Python :: 3.5
Classifier: Programming Language :: Python :: 3.6
Classifier: Programming Language :: Python :: 3.7
Classifier: Programming Language :: Python :: 3.8
Classifier: Topic :: Software Development :: Libraries :: Python Modules
